EatWhat/__init__.py
EatWhat/__main__.py
EatWhat/cli.py
EatWhat/osprofile.py
EatWhat/random.py
EatWhat-0.1.0.dist-info/AUTHORS
EatWhat-0.1.0.dist-info/METADATA
EatWhat-0.1.0.dist-info/WHEEL
EatWhat-0.1.0.dist-info/entry_points.txt
EatWhat-0.1.0.dist-info/pbr.json
EatWhat-0.1.0.dist-info/top_level.txt
EatWhat-0.1.0.dist-info/RECORD
