Metadata-Version: 2.1
Name: EatWhat
Version: 0.1.0
Summary: awsome project created by pycman.
Home-page: http://example.com
Author: singein
Author-email: singein@outlook.com
License: MIT
Platform: UNKNOWN
Requires-Dist: pycman
